__init__.py
editor.py
nanote.py
settings.py
setup.py
nanote.egg-info/PKG-INFO
nanote.egg-info/SOURCES.txt
nanote.egg-info/dependency_links.txt
nanote.egg-info/entry_points.txt
nanote.egg-info/top_level.txt