Metadata-Version: 1.0
Name: nanote
Version: 0.1.3
Summary: nanote terminal note-taking software
Home-page: https://github.com/hourchallenge/nanote
Author: Ben Morris
Author-email: ben@bendmorris.com
License: UNKNOWN
Platform: UNKNOWN
